[{"Id":1,"Name":"Emil","Date":"2023-02-02T00:00:00","BookedRoom":{"ID":2,"Name":"Committment","Seats":6,"BookedBy":null}},{"Id":2,"Name":"asd","Date":"2023-02-13T00:00:00","BookedRoom":{"ID":3,"Name":"Innovation","Seats":8,"BookedBy":null}},{"Id":3,"Name":"Daniel","Date":"2023-02-13T00:00:00","BookedRoom":{"ID":3,"Name":"Innovation","Seats":8,"BookedBy":null}},{"Id":4,"Name":"Daniel","Date":"2023-02-13T00:00:00","BookedRoom":{"ID":4,"Name":"Inspired","Seats":8,"BookedBy":null}},{"Id":5,"Name":"admin","Date":"2023-02-13T00:00:00","BookedRoom":{"ID":4,"Name":"Inspired","Seats":8,"BookedBy":null}},{"Id":9,"Name":"Mallorca","Date":"2023-02-17T00:00:00","BookedRoom":{"ID":1,"Name":"Collaboration","Seats":6,"BookedBy":null}},{"Id":11,"Name":"danielkjellberg@hotmail.com","Date":"2023-02-17T00:00:00","BookedRoom":{"ID":1,"Name":"Collaboration","Seats":6,"BookedBy":null}},{"Id":12,"Name":"asd","Date":"2023-02-17T00:00:00","BookedRoom":{"ID":1,"Name":"Collaboration","Seats":6,"BookedBy":null}},{"Id":13,"Name":"admin","Date":"2023-02-17T00:00:00","BookedRoom":{"ID":1,"Name":"Collaboration","Seats":6,"BookedBy":null}},{"Id":16,"Name":"Daniel","Date":"2023-02-17T00:00:00","BookedRoom":{"ID":1,"Name":"Collaboration","Seats":6,"BookedBy":null}},{"Id":21,"Name":"Daniel","Date":"2023-02-15T00:00:00","BookedRoom":{"ID":2,"Name":"Committment","Seats":6,"BookedBy":null}},{"Id":22,"Name":"Daniel","Date":"2023-02-15T00:00:00","BookedRoom":{"ID":2,"Name":"Committment","Seats":6,"BookedBy":null}},{"Id":23,"Name":"Daniel","Date":"2023-02-15T00:00:00","BookedRoom":{"ID":1,"Name":"Collaboration","Seats":6,"BookedBy":null}},{"Id":24,"Name":"Daniel","Date":"2023-02-16T00:00:00","BookedRoom":{"ID":1,"Name":"Collaboration","Seats":6,"BookedBy":null}}]
